qfpy/__init__.py
qfpy/character.py
qfpy/crypto.py
qfpy/excel.py
qfpy/exif.py
qfpy/ffmpeg.py
qfpy/folder.py
qfpy/function.py
qfpy/log.py
qfpy/net.py
qfpy/output.py
qfpy/pdf.py
qfpy/process.py
qfpy/system.py
qfpy/图片.py
qfpy/文件.py
qfpy/游戏.py
qfpy-17.2.3.dist-info/METADATA
qfpy-17.2.3.dist-info/WHEEL
qfpy-17.2.3.dist-info/top_level.txt
qfpy-17.2.3.dist-info/RECORD
