Metadata-Version: 2.1
Name: qfpy
Version: 17.2.3
Summary: qf 的 py 函数库。版本号规则：API变动.新功能.优化和修复
Author-email: gqf <gqfol@outlook.com>
Classifier: Programming Language :: Python :: 3
Requires-Dist: psutil
Requires-Dist: pycryptodome
Requires-Dist: loguru
Requires-Dist: pymupdf
Requires-Dist: pyautogui
Requires-Dist: pillow
Requires-Dist: pywin32
Requires-Dist: numpy
Requires-Dist: ppocr-onnx
